honestjson/__init__.py
honestjson/main.py
honestjson-0.1.3.dist-info/METADATA
honestjson-0.1.3.dist-info/WHEEL
honestjson-0.1.3.dist-info/top_level.txt
honestjson-0.1.3.dist-info/RECORD
