Metadata-Version: 2.1
Name: honestjson
Version: 0.1.3
Summary: This package is made for dependency confusion demonstration purposes only. While it does nothing harmful (it puts a text file on your machine), it is not recommended you install it, because it is useless.
